MANIFEST.in
README.rst
requirements.txt
setup.py
coscmd/__init__.py
coscmd/cos_auth.py
coscmd/cos_client.py
coscmd/cos_cmd.py
coscmd/cos_comm.py
coscmd/cos_global.py
coscmd/cos_sync.py
coscmd/cos_threadpool.py
coscmd/test.py
innercoscmd.egg-info/PKG-INFO
innercoscmd.egg-info/SOURCES.txt
innercoscmd.egg-info/dependency_links.txt
innercoscmd.egg-info/entry_points.txt
innercoscmd.egg-info/requires.txt
innercoscmd.egg-info/top_level.txt