Metadata-Version: 1.0
Name: innercoscmd
Version: 2.0.0.2
Summary: simple command for cos
Home-page: https://www.qcloud.com/
Author: maysonshen, lewzylu
Author-email: 327874225@qq.com
License: MIT
Platform: UNKNOWN
